accessly/__init__.py
accessly/config.py
accessly/core.py
accessly/accessibilities/__init__.py
accessly/accessibilities/alttext.py
accessly/accessibilities/colorblind.py
accessly/accessibilities/leftright.py
accessly/accessibilities/legiblefont.py
accessly/accessibilities/linestlyes.py
accessly-0.0.2.dist-info/licenses/LICENSE
accessly-0.0.2.dist-info/METADATA
accessly-0.0.2.dist-info/WHEEL
accessly-0.0.2.dist-info/top_level.txt
accessly-0.0.2.dist-info/RECORD
