Metadata-Version: 2.4
Name: accessly
Version: 0.0.2
License-File: LICENSE
Requires-Dist: matplotlib
Requires-Dist: numpy
Requires-Dist: pyfonts
Requires-Dist: pytest
Dynamic: license-file
